[
    {
        "id": "preamble1",
        "desc": "Однажды вы пошли гулять в лес и набрели там на удивительную поляну. Вся покрытая пышными цветами, она была очень красивой. От сильного запаха цветов и небывалой тишины клонило в сон. Вы не удержались и уснули…",
        "next": "preamble2"
    },
    {
        "id": "preamble2",
        "desc": "Вам снились странные сны — как будто вас куда-то тянет, далеко-далеко, на другой край вселенной. Несмотря на это, проснулись вы вполне отдохновшим. Сев и протерев глаза, вы обнаружили, что находитесь на очень похожей, но все-таки другой поляне. Вы никогда не видели таких цветов и деревьев.",
        "next": "preamble3"
    },
    {
        "id": "preamble3",
        "desc": "Идя по тропинке, вы постепенно вышли на опушку и не смогли сдержать изумленный возглас. Это не ваш город!",
        "next": "preamble4"
    }

]